{
  "basics": {
    "name": "Shangqing Tong",
    "label": "PhD student",
    "image": "",
    "email": "shangqing.tong@sjtu.edu.cn",
    "phone": "11122223333",
    "url": "https://noeltong.github.io",
    "summary": "A German-born theoretical physicist, widely ranked among the greatest and most influential scientists of all time",
    "location": {
      "address": "800 Dongchuan Rd.",
      "postalCode": "200240",
      "city": "Shanghai",
      "countryCode": "China",
      "region": "Minhang Dist."
    },
    "profiles": [
      {
        "network": "Google Scholar",
        "username": "Shangqing Tong",
        "url": "https://scholar.google.com/citations?hl=zh-CN&user=-TaP8h4AAAAJ"
      },
      {
        "network": "ORCID",
        "username": "Shangqing Tong",
        "url": "https://orcid.org/0009-0001-9961-7822"
      }
    ]
  },
  "work": [
    {
      "name": "Central Research Institute, United Imaging Healthcare",
      "position": "Software Engineer",
      "url": "https://global.united-imaging.com/en/",
      "startDate": "2023-10-19",
      "endDate": "2024-07-05",
      "summary": "During my internship at Central Research Institute of United Imaging, my work mainly focused on the quantitative analysis algorithms of parametric imaging of dynamic positron emission tomography (dPET) imaging with patient data from uEXPLORER, a total body PET/CT scanner, under the supervision of Prof.~Yun Zhou.",
      "highlights": ["Dual-tracer time-activity curve separation with machine learning algorithms.", "Accelerating irreversible 2-tissue compartment model with CUDA and PyTorch.", "Development of automatic PET/CT parametric imaging and time-activity curve calculation (including regions of interest of brain and tissues of total body) pipeline with CT segmentation."]
    }
  ],
  "volunteer": [
    {
      "organization": "People's Climate March",
      "location": "Zurich, Switzerland",
      "position": "Lead Organizer",
      "url": "https://example.com",
      "startDate": "2014-04-01",
      "endDate": "2015-07-01",
      "summary": "Lead organizer for the New York City branch of the People's Climate March, the largest climate march in history.",
      "highlights": ["Awarded 'Climate Hero' award by Greenpeace for my efforts organizing the march.", "Men of the year 2014 by Time magazine"]
    }
  ],
  "education": [
    {
      "institution": "Shanghai Jiao Tong University",
      "location": "Shanghai, China",
      "url": "https://en.sjtu.edu.cn/",
      "area": "Electrical Engineering",
      "studyType": "PhD",
      "startDate": "2024-09-01",
      "endDate": "2028-07-01",
      "score": "10",
      "courses": ["Optics and Photonics"]
    },
    {
        "institution": "ShanghaiTech University",
        "location": "Shanghai, China",
        "url": "https://www.shanghaitech.edu.cn/eng/",
        "area": "Electrical Engineering",
        "studyType": "MSE",
        "startDate": "2021-09-01",
        "endDate": "2024-07-01",
        "score": "10",
        "courses": ["Machine Learning", "Matrix Calculation", "Digital Image Processing"]
    },
    {
        "institution": "Jiangnan University",
        "location": "Wuxi, Jiangsu, China",
        "url": "https://www.jiangnan.edu.cn/",
        "area": "Communication Engineering",
        "studyType": "BS",
        "startDate": "2017-09-01",
        "endDate": "2021-07-01",
        "score": "10",
        "courses": ["Signals and Systems", "Digital Signal Processing", "Calculus"]
    }
  ],
  "awards": [
    {
      "title": "The Third Prize Scholarship",
      "date": "2018-11-11",
      "awarder": "Jiangnan University",
      "url": "https://www.nobelprize.org/prizes/physics/1921/einstein/biographical/",
      "summary": "The Nobel Prizes are five separate prizes that, according to Alfred Nobel's will of 1895, are awarded to 'those who, during the preceding year, have conferred the greatest benefit to humankind.'"
    }
  ],
  "certificates": [
    {
      "name": "Matrix Calculation",
      "date": "2021-12-01",
      "issuer": "ShanghaiTech University",
      "url": "https://si231.sist.shanghaitech.edu.cn/index.html",
      "icon": "fa-solid fa-location-dot"
    },
    {
      "name": "Machine Learning",
      "date": "2021-12-01",
      "issuer": "ShanghaiTech University",
      "icon": "fa-solid fa-tag"
    }
  ],
  "publications": [
    {
      "name": "Photoacoustic imaging plus X: a review",
      "publisher": "Journal of Biomedical Optics",
      "releaseDate": "2024-01-15",
      "url": "https://www.spiedigitallibrary.org/journals/journal-of-biomedical-optics/volume-29/issue-S1/S11513/Photoacoustic-imaging-plus-X-a-review/10.1117/1.JBO.29.S1.S11513.short",
      "summary": "A brief review of deep learning applications in photoacoustic imaging among recent years. I completed Section 6 of the review paper."
    }
  ],
  "skills": [
    {
      "name": "Deep Learning",
      "level": "Familliar",
      "icon": "fa-solid fa-hashtag",
      "keywords": [
        "PyTorch",
        "JAX"
      ]
    }
  ],
  "languages": [
    {
      "language": "Mandarin",
      "fluency": "Native speaker",
      "icon": ""
    },
    {
      "language": "English",
      "fluency": "Fluent",
      "icon": ""
    }
  ],
  "interests": [
    {
      "name": "Deep Learning Applications in Biomedical Imaging",
      "icon": "fa-solid fa-tag",
      "keywords": [
        "Deep Learning",
        "Biomedical Engineering",
        "Medical Imaging"
      ]
    },
    {
      "name": "Photonic Neural Network",
      "icon": "fa-solid fa-laptop",
      "keywords": [
        "Deep Learning",
        "Optical Computing"
      ]
    }
  ],
  "references": [
    {
      "name": "Professor Sung-Liang Chen",
      "icon": "fa-solid fa-laptop",
      "reference": "My advisor in PhD research."
    },
    {
      "name": "Professor Fei Gao",
      "icon": "fa-solid fa-thumbtack",
      "reference": "My advisor in MSE research."
    }
  ],
  "projects": [
    {
      "name": "CATL Battery CT Scan Reconstruction",
      "summary": "Reconstruct undersampled CT scan images of batteries.",
      "highlights": ["Inverse Problem"],
      "startDate": "2024-06-20",
      "endDate": "Present"
    }
  ]
}
